retina_face-0.0.16.data/data/README.md
retina_face-0.0.16.data/data/package_info.json
retina_face-0.0.16.data/data/requirements.txt
retinaface/RetinaFace.py
retinaface/__init__.py
retinaface/commons/__init__.py
retinaface/commons/logger.py
retinaface/commons/package_utils.py
retinaface/commons/postprocess.py
retinaface/commons/preprocess.py
retinaface/model/__init__.py
retinaface/model/retinaface_model.py
retina_face-0.0.16.dist-info/LICENSE
retina_face-0.0.16.dist-info/METADATA
retina_face-0.0.16.dist-info/WHEEL
retina_face-0.0.16.dist-info/top_level.txt
retina_face-0.0.16.dist-info/RECORD
