Metadata-Version: 2.1
Name: retina-face
Version: 0.0.16
Summary: RetinaFace: Deep Face Detection Framework in TensorFlow for Python
Home-page: https://github.com/serengil/retinaface
Author: Sefik Ilkin Serengil
Author-email: serengil@gmail.com
License: UNKNOWN
Platform: UNKNOWN
Classifier: Programming Language :: Python :: 3
Classifier: License :: OSI Approved :: MIT License
Classifier: Operating System :: OS Independent
Requires-Python: >=3.5.5
License-File: LICENSE
Requires-Dist: numpy (>=1.14.0)
Requires-Dist: gdown (>=3.10.1)
Requires-Dist: Pillow (>=5.2.0)
Requires-Dist: opencv-python (>=3.4.4)
Requires-Dist: tensorflow (>=1.9.0)
